decidim/__init__.py
decidim/electionguard/__init__.py
decidim/electionguard/bulletin_board.py
decidim/electionguard/common.py
decidim/electionguard/dummy_scheduler.py
decidim/electionguard/messages.py
decidim/electionguard/serializable.py
decidim/electionguard/trustee.py
decidim/electionguard/utils.py
decidim/electionguard/voter.py
bulletin_board_election_guard-0.1.0.dist-info/LICENSE
bulletin_board_election_guard-0.1.0.dist-info/METADATA
bulletin_board_election_guard-0.1.0.dist-info/WHEEL
bulletin_board_election_guard-0.1.0.dist-info/top_level.txt
bulletin_board_election_guard-0.1.0.dist-info/RECORD
