Metadata-Version: 2.1
Name: bulletin-board-election-guard
Version: 0.1.0
Summary: The Python wrapper used by the ElectionGuard voting scheme implementation for the Decidim Bulletin Board.
Home-page: http://github.com/codegram/decidim.electionguard
Author: Codegram
Author-email: leo@codegram.com
License: MIT
Platform: UNKNOWN
Requires-Dist: electionguard (==1.1.15)
Requires-Dist: jsons (==1.2)
